fasta_reader/__init__.py
fasta_reader/anyfile.py
fasta_reader/errors.py
fasta_reader/formatter.py
fasta_reader/item.py
fasta_reader/read_fasta.py
fasta_reader/reader.py
fasta_reader/uri.py
fasta_reader/write_fasta.py
fasta_reader/writer.py
fasta_reader-3.1.1.dist-info/LICENSE
fasta_reader-3.1.1.dist-info/METADATA
fasta_reader-3.1.1.dist-info/WHEEL
fasta_reader-3.1.1.dist-info/RECORD
