Metadata-Version: 2.1
Name: fasta-reader
Version: 3.1.1
Summary: FASTA file reader/writer.
Home-page: https://github.com/EBI-Metagenomics/fasta-reader
License: MIT
Author: Danilo Horta
Author-email: fdanilo.horta@pm.me
Requires-Python: >=3.9,<4.0
Classifier: License :: OSI Approved :: MIT License
Classifier: Programming Language :: Python :: 3
Classifier: Programming Language :: Python :: 3.9
Classifier: Programming Language :: Python :: 3.10
Classifier: Programming Language :: Python :: 3.11
Classifier: Programming Language :: Python :: 3.12
Classifier: Programming Language :: Python :: 3.13
Requires-Dist: fsspec (>=2024.5.0)
Project-URL: Repository, https://github.com/EBI-Metagenomics/fasta-reader
